odoo/addons/account_analytic_line_name_text/README.rst
odoo/addons/account_analytic_line_name_text/__init__.py
odoo/addons/account_analytic_line_name_text/__manifest__.py
odoo/addons/account_analytic_line_name_text/i18n/account_analytic_line_name_text.pot
odoo/addons/account_analytic_line_name_text/models/__init__.py
odoo/addons/account_analytic_line_name_text/models/account_analytic_line.py
odoo/addons/account_analytic_line_name_text/readme/CONTRIBUTORS.rst
odoo/addons/account_analytic_line_name_text/readme/DESCRIPTION.rst
odoo/addons/account_analytic_line_name_text/static/description/icon.png
odoo/addons/account_analytic_line_name_text/static/description/index.html
odoo12_addon_account_analytic_line_name_text-12.0.1.0.0.99.dev5.dist-info/METADATA
odoo12_addon_account_analytic_line_name_text-12.0.1.0.0.99.dev5.dist-info/WHEEL
odoo12_addon_account_analytic_line_name_text-12.0.1.0.0.99.dev5.dist-info/top_level.txt
odoo12_addon_account_analytic_line_name_text-12.0.1.0.0.99.dev5.dist-info/RECORD
